Workbook

Sheet Summary
A1: WashRoute pricing change — April 2026 model
A2: Window: April 2026 only (first complete month on WashRoute) · Delivery price list
A4: THE BOTTOM LINE
A5: Current pricing baseline (April actual) | B5: =Scenarios!B22 -> 150152.25 | D5: vs current | E5: 1,489 orders, 2,227 bags, 47,456 lbs
A6: Rate increase only ($59 → $65, no volume drop, no subs) | B6: =Scenarios!C22 -> 163514.25 | C6: =Scenarios!C24 -> 0.088989675 | D6: vs current | E6: $13,362 lift / mo
A7: Rate increase + 0% volume drop, no subs | B7: =Scenarios!D22 -> 163514.25 | C7: =Scenarios!D24 -> 0.088989675 | D7: vs current | E7: Same as B with no drop assumption
A8: CANNIBALIZATION: Top 200 subscribe, 0% drop on bottom 440 | B8: =Scenarios!E22 -> 148518.2 | C8: =Scenarios!E24 -> -0.010882621 | D8: vs current | E8: Your scenario — top 200 switch, others unchanged
A9: GROWTH: 200 NEW subscribers, 0% drop on existing per-bag | B9: =Scenarios!F22 -> 218514.25 | C9: =Scenarios!F24 -> 0.45528455 | D9: vs current | E9: 200 new customers acquired (not converted)
A12: ANNUALIZED VIEW (April × 12)
A13: Current pricing | B13: =Scenarios!B26 -> 1801827 | D13: annual
A14: Rate increase only (no drop) | B14: =Scenarios!C26 -> 1962171 | C14: =Scenarios!C26-Scenarios!B26 -> 160344 | D14: vs baseline
A15: Rate increase + 0% drop (same as no subs) | B15: =Scenarios!D26 -> 1962171 | C15: =Scenarios!D26-Scenarios!B26 -> 160344 | D15: vs baseline
A16: Cannibalization scenario | B16: =Scenarios!E26 -> 1782218.4 | C16: =Scenarios!E26-Scenarios!B26 -> -19608.6 | D16: vs baseline
A17: Growth scenario | B17: =Scenarios!F26 -> 2622171 | C17: =Scenarios!F26-Scenarios!B26 -> 820344 | D17: vs baseline
A20: KEY INSIGHTS
A21: 1. Rate increase alone is the strongest revenue lever
A22: Lifting per-bag from $59 → $65 with NO subscription adds $22,270/month at current April volume (annualized: $267k/year). Threshold stays at 25 lbs so customer-facing math doesn't change — just a $10 increase per bag.
A24: 2. Cannibalization scenario barely breaks even — the rate lift is gone
A25: Your top 200 customers spent $88,809 in April. Putting them all on $275/mo subs gives you $55,000 in base + $26,673 in overage = $81,673 — $7,136 LESS than they pay today, and $20,236 less than they'd pay under the new $69 rate. Bottom 440 stays unchanged at $70,513 under new pricing. Total: $152,186 / month → +$2,034 vs current ($24k/year). The whole $267k/year rate-increase lift evaporates into the subscription discount you're giving your best customers.
A27: 3. Top 200 = 59% of revenue, so converting them is high-stakes
A28: Top 200 = 31% of customers but 59% of revenue ($88,809 of $150,152). Replacing that with a flat-fee subscription trades high-margin variable revenue for predictable low-margin recurring revenue. The math only works if subscription unlocks materially MORE orders per customer than they're placing today (it might — flat fee removes friction).
A30: 4. Growth scenario (200 NEW subscribers) is where the real upside lives
A31: If those 200 subs are net-new customers (not conversions from your top 200), revenue jumps to ~$227k/month at 0% drop, or +$919k/year vs current. That's the ONLY scenario where the subscription is genuinely additive — requires acquisition marketing to bring in customers who don't currently use you.
A33: 5. Watch the heavy hitters — Pena, Ojeba, Ray Thomas, CCELC, Baby Lee
A34: Top 5 customers (Nicole Pena, Onimisi Ojeba, Ray Thomas, Kidango-CCELC, Baby Lee) average 401 lbs each in April. Under subscription they'd each pay ~$275 + ~$903 overage = ~$1,178/mo, vs the ~$1,165 they pay today and ~$1,300 they'd pay under the new rate. Pena alone saves $942/mo by subscribing — that's ~$11k/yr from one customer. Kidango is on a commercial contract and should be excluded from the consumer subscription anyway.
A37: RECOMMENDATIONS
... A43: • Announce the rate increase + subscription option simultaneously so per-bag customers feel they have an alternative — softens the price-hike narrative.

Sheet Assumptions
A1: Pricing Model — Assumptions (April 2026 baseline)
A3: Inputs (BLUE cells — change to test scenarios)
A4: Window — month | B4: April 2026 | C4: First complete month on WashRoute
A5: Lookback months | B5: 1 | C5: Period being modeled
A7: CURRENT — per-bag rate ($) | B7: 59 | C7: Wash & Fold base price
A8: CURRENT — bag weight threshold (lbs) | B8: 25 | C8: Lbs included in per-bag rate
A9: CURRENT — overage rate ($/lb) | B9: 3 | C9: Beyond threshold
A10: CURRENT — pickup/delivery fee ($) | B10: 9.95 | C10: Per order
A12: NEW — per-bag rate ($) | B12: 65 | C12: RAISED from $59 → $65 (+10%)
A13: NEW — bag weight threshold (lbs) | B13: 25 | C13: Unchanged
A14: NEW — overage rate ($/lb) | B14: 3 | C14: Unchanged
A15: NEW — pickup/delivery fee ($) | B15: 9.95 | C15: Unchanged
A17: Subscription — monthly fee ($) | B17: 275 | C17: Flat fee per subscriber per month
A18: Subscription — included lbs/month | B18: 100 | C18: Above this, charged at overage rate
A19: Subscription — overage rate ($/lb) | B19: 3 | C19: Same as per-bag overage
... A22: Subscriber count target | B22: 200 | C22: From existing top-200 by lbs
A24: Color legend
A25: Blue text = input (edit me)
A26: Black text = formula
A27: Green text = pulled from another tab

Sheet Customer Detail (Top 200)
A1: Top 200 customers by lbs — April 2026
A2: These are the 200 customers assumed to subscribe in the cannibalization scenario
A4: # | B4: Customer | C4: Orders | D4: Bags | E4: Lbs | F4: Current rev | G4: Rate-increase Δ | H4: New per-bag rev | I4: Sub base | J4: Sub overage | K4: Sub total | L4: Customer would save?
A5: 1 | B5: Nicole Pena | C5: 2 | D5: 35 | E5: 506 | F5: 2084.9 | G5: =D5*(new_rate-cur_rate) -> 210 | H5: =F5+G5 -> 2294.9 | I5: =sub_fee -> 275 | J5: =MAX(0, E5-sub_lbs)*sub_overage -> 1218 | K5: =I5+J5 -> 1493 | L5: =IF(K5<H5,"Yes — saves $"&TEXT(H5-K5,"0"),"No") -> Yes — saves $802
A6: 2 | B6: Onimisi Ojeba | C6: 4 | D6: 16 | E6: 432 | F6: 1079.8 | G6: =D6*(new_rate-cur_rate) -> 96 | H6: =F6+G6 -> 1175.8 | I6: =sub_fee -> 275 | J6: =MAX(0, E6-sub_lbs)*sub_overage -> 996 | K6: =I6+J6 -> 1271 | L6: =IF(K6<H6,"Yes — saves $"&TEXT(H6-K6,"0"),"No") -> No
A7: 3 | B7: Ray Thomas | C7: 9 | D7: 22 | E7: 399 | F7: 1367.55 | G7: =D7*(new_rate-cur_rate) -> 132 | H7: =F7+G7 -> 1499.55 | I7: =sub_fee -> 275 | J7: =MAX(0, E7-sub_lbs)*sub_overage -> 897 | K7: =I7+J7 -> 1172 | L7: =IF(K7<H7,"Yes — saves $"&TEXT(H7-K7,"0"),"No") -> Yes — saves $328
A8: 4 | B8: Kidango - CCELC | C8: 4 | D8: 31 | E8: 341 | F8: 1262.95 | G8: =D8*(new_rate-cur_rate) -> 186 | H8: =F8+G8 -> 1448.95 | I8: =sub_fee -> 275 | J8: =MAX(0, E8-sub_lbs)*sub_overage -> 723 | K8: =I8+J8 -> 998 | L8: =IF(K8<H8,"Yes — saves $"&TEXT(H8-K8,"0"),"No") -> Yes — saves $451
A9: 5 | B9: Baby Lee | C9: 5 | D9: 17 | E9: 328 | F9: 1032.75 | G9: =D9*(new_rate-cur_rate) -> 102 | H9: =F9+G9 -> 1134.75 | I9: =sub_fee -> 275 | J9: =MAX(0, E9-sub_lbs)*sub_overage -> 684 | K9: =I9+J9 -> 959 | L9: =IF(K9<H9,"Yes — saves $"&TEXT(H9-K9,"0"),"No") -> Yes — saves $176
A10: 6 | B10: OAKLAND ROOTS & SOUL | C10: 3 | D10: 17 | E10: 309 | F10: 481.95 | G10: =D10*(new_rate-cur_rate) -> 102 | H10: =F10+G10 -> 583.95 | I10: =sub_fee -> 275 | J10: =MAX(0, E10-sub_lbs)*sub_overage -> 627 | K10: =I10+J10 -> 902 | L10: =IF(K10<H10,"Yes — saves $"&TEXT(H10-K10,"0"),"No") -> No
A11: 7 | B11: Alice Neels | C11: 4 | D11: 11 | E11: 277 | F11: 701.8 | G11: =D11*(new_rate-cur_rate) -> 66 | H11: =F11+G11 -> 767.8 | I11: =sub_fee -> 275 | J11: =MAX(0, E11-sub_lbs)*sub_overage -> 531 | K11: =I11+J11 -> 806 | L11: =IF(K11<H11,"Yes — saves $"&TEXT(H11-K11,"0"),"No") -> No
A12: 8 | B12: Nathan Darling | C12: 4 | D12: 12 | E12: 277 | F12: 745.8 | G12: =D12*(new_rate-cur_rate) -> 72 | H12: =F12+G12 -> 817.8 | I12: =sub_fee -> 275 | J12: =MAX(0, E12-sub_lbs)*sub_overage -> 531 | K12: =I12+J12 -> 806 | L12: =IF(K12<H12,"Yes — saves $"&TEXT(H12-K12,"0"),"No") -> Yes — saves $12
A13: 9 | B13: AnnaMaria Knapp | C13: 5 | D13: 19 | E13: 268 | F13: 1150.75 | G13: =D13*(new_rate-cur_rate) -> 114 | H13: =F13+G13 -> 1264.75 | I13: =sub_fee -> 275 | J13: =MAX(0, E13-sub_lbs)*sub_overage -> 504 | K13: =I13+J13 -> 779 | L13: =IF(K13<H13,"Yes — saves $"&TEXT(H13-K13,"0"),"No") -> Yes — saves $486
A14: 10 | B14: Ruby Anderson | C14: 7 | D14: 14 | E14: 256 | F14: 875.65 | G14: =D14*(new_rate-cur_rate) -> 84 | H14: =F14+G14 -> 959.65 | I14: =sub_fee -> 275 | J14: =MAX(0, E14-sub_lbs)*sub_overage -> 468 | K14: =I14+J14 -> 743 | L14: =IF(K14<H14,"Yes — saves $"&TEXT(H14-K14,"0"),"No") -> Yes — saves $217
A15: 11 | B15: Parker Thomas | C15: 4 | D15: 9 | E15: 254 | F15: 598.8 | G15: =D15*(new_rate-cur_rate) -> 54 | H15: =F15+G15 -> 652.8 | I15: =sub_fee -> 275 | J15: =MAX(0, E15-sub_lbs)*sub_overage -> 462 | K15: =I15+J15 -> 737 | L15: =IF(K15<H15,"Yes — saves $"&TEXT(H15-K15,"0"),"No") -> No
A16: 12 | B16: Laura Guevara | C16: 4 | D16: 12 | E16: 250 | F16: 783.8 | G16: =D16*(new_rate-cur_rate) -> 72 | H16: =F16+G16 -> 855.8 | I16: =sub_fee -> 275 | J16: =MAX(0, E16-sub_lbs)*sub_overage -> 450 | K16: =I16+J16 -> 725 | L16: =IF(K16<H16,"Yes — saves $"&TEXT(H16-K16,"0"),"No") -> Yes — saves $131
... A204: 200 | B204: Wyn Lee | C204: 3 | D204: 7 | E204: 87 | F204: 493.85 | G204: =D204*(new_rate-cur_rate) -> 42 | H204: =F204+G204 -> 535.85 | I204: =sub_fee -> 275 | J204: =MAX(0, E204-sub_lbs)*sub_overage -> 0 | K204: =I204+J204 -> 275 | L204: =IF(K204<H204,"Yes — saves $"&TEXT(H204-K204,"0"),"No") -> Yes — saves $261
B205: TOTAL — Top 200 | C205: =SUM(C5:C204) -> 758 | D205: =SUM(D5:D204) -> 1313 | E205: =SUM(E5:E204) -> 28623 | F205: =SUM(F5:F204) -> 89055 | G205: =SUM(G5:G204) -> 7878 | H205: =SUM(H5:H204) -> 96933 | I205: =SUM(I5:I204) -> 55000 | J205: =SUM(J5:J204) -> 26673 | K205: =SUM(K5:K204) -> 81673

Sheet Scenarios
A1: April 2026 — Revenue scenarios (1 month)
A2: Comparing 4 scenarios against the April baseline
A4: (Aggregates — read-only)
A5: April total: orders | B5: 1489
A6: April total: customers | B6: 640
A7: April total: bags | B7: 2227
A8: April total: lbs | B8: 47456
A9: April total: revenue | B9: 150152.25
A10: Top 200: bags | B10: 1310
A11: Top 200: lbs | B11: 28623
A12: Top 200: revenue (current) | B12: 88809.05
A13: Bottom 440: bags | B13: 917
A14: Bottom 440: lbs | B14: 18833
A15: Bottom 440: revenue (current) | B15: 61343.2
A17: Scenario comparison
A18: Metric | B18: A. Current | C18: B. New rate, no drop, no subs | D18: C. New rate, with drop, no subs | E18: D. CANNIBALIZATION (200 top subs) | F18: E. GROWTH (200 NEW subs) | G18: Notes
A19: Per-bag revenue from non-subs | B19: =apr_rev -> 150152.25 | C19: =apr_rev + apr_bags*(new_rate-cur_rate) -> 163514.25 | D19: =(apr_rev + apr_bags*(new_rate-cur_rate))*(1-vol_drop) -> 163514.25 | E19: =(b440_rev + b440_bags*(new_rate-cur_rate))*(1-vol_drop) -> 66845.2 | F19: =(apr_rev + apr_bags*(new_rate-cur_rate))*(1-vol_drop) -> 163514.25 | G19: Bottom 440 in scenario D; everyone in C and E
A20: Subscription base revenue | B20: =0 -> 0 | C20: =0 -> 0 | D20: =0 -> 0 | E20: =sub_count*sub_fee -> 55000 | F20: =sub_count*sub_fee -> 55000 | G20: 200 × $275 = $55,000/month
A21: Subscription overage revenue | B21: =0 -> 0 | C21: =0 -> 0 | D21: =0 -> 0 | E21: =SUM('Customer Detail (Top 200)'!J5:J204) -> 26673 | F21: =0 -> 0 | G21: D: actual overage from top 200's April lbs; E: assumes new subs avg 50 lbs/mo
A22: TOTAL revenue | B22: =B19+B20+B21 -> 150152.25 | C22: =C19+C20+C21 -> 163514.25 | D22: =D19+D20+D21 -> 163514.25 | E22: =E19+E20+E21 -> 148518.2 | F22: =F19+F20+F21 -> 218514.25
A23: vs Current — $ | B23: =B22-$B$22 -> 0 | C23: =C22-$B$22 -> 13362 | D23: =D22-$B$22 -> 13362 | E23: =E22-$B$22 -> -1634.05 | F23: =F22-$B$22 -> 68362
A24: vs Current — % | B24: =B22/$B$22-1 -> 0 | C24: =C22/$B$22-1 -> 0.088989675 | D24: =D22/$B$22-1 -> 0.088989675 | E24: =E22/$B$22-1 -> -0.010882621 | F24: =F22/$B$22-1 -> 0.45528455
A26: Annualized (× 12) | B26: =B22*12 -> 1801827 | C26: =C22*12 -> 1962171 | D26: =D22*12 -> 1962171 | E26: =E22*12 -> 1782218.4 | F26: =F22*12 -> 2622171 | G26: Rough projection — assumes April volume holds

Sheet Sensitivity
A1: Sensitivity — revenue by volume drop %
A2: How does monthly revenue change at different volume-drop assumptions?
A4: Volume drop | B4: A. Current | C4: B. New rate (no drop) | D4: C. New rate + drop | E4: D. Cannibalization | F4: E. Growth
A5: 0 | B5: =apr_rev -> 150152.25 | C5: =apr_rev + apr_bags*(new_rate-cur_rate) -> 163514.25 | D5: =(apr_rev + apr_bags*(new_rate-cur_rate))*(1-A5) -> 163514.25 | E5: =(b440_rev + b440_bags*(new_rate-cur_rate))*(1-A5) + sub_count*sub_fee + SUM('Customer Detail (Top 200)'!J5:J204) -> 148518.2 | F5: =(apr_rev + apr_bags*(new_rate-cur_rate))*(1-A5) + sub_count*sub_fee -> 218514.25
A6: 0.025 | B6: =apr_rev -> 150152.25 | C6: =apr_rev + apr_bags*(new_rate-cur_rate) -> 163514.25 | D6: =(apr_rev + apr_bags*(new_rate-cur_rate))*(1-A6) -> 159426.39 | E6: =(b440_rev + b440_bags*(new_rate-cur_rate))*(1-A6) + sub_count*sub_fee + SUM('Customer Detail (Top 200)'!J5:J204) -> 146847.07 | F6: =(apr_rev + apr_bags*(new_rate-cur_rate))*(1-A6) + sub_count*sub_fee -> 214426.39
A7: 0.05 | B7: =apr_rev -> 150152.25 | C7: =apr_rev + apr_bags*(new_rate-cur_rate) -> 163514.25 | D7: =(apr_rev + apr_bags*(new_rate-cur_rate))*(1-A7) -> 155338.54 | E7: =(b440_rev + b440_bags*(new_rate-cur_rate))*(1-A7) + sub_count*sub_fee + SUM('Customer Detail (Top 200)'!J5:J204) -> 145175.94 | F7: =(apr_rev + apr_bags*(new_rate-cur_rate))*(1-A7) + sub_count*sub_fee -> 210338.54
A8: 0.075 | B8: =apr_rev -> 150152.25 | C8: =apr_rev + apr_bags*(new_rate-cur_rate) -> 163514.25 | D8: =(apr_rev + apr_bags*(new_rate-cur_rate))*(1-A8) -> 151250.68 | E8: =(b440_rev + b440_bags*(new_rate-cur_rate))*(1-A8) + sub_count*sub_fee + SUM('Customer Detail (Top 200)'!J5:J204) -> 143504.81 | F8: =(apr_rev + apr_bags*(new_rate-cur_rate))*(1-A8) + sub_count*sub_fee -> 206250.68
A9: 0.1 | B9: =apr_rev -> 150152.25 | C9: =apr_rev + apr_bags*(new_rate-cur_rate) -> 163514.25 | D9: =(apr_rev + apr_bags*(new_rate-cur_rate))*(1-A9) -> 147162.83 | E9: =(b440_rev + b440_bags*(new_rate-cur_rate))*(1-A9) + sub_count*sub_fee + SUM('Customer Detail (Top 200)'!J5:J204) -> 141833.68 | F9: =(apr_rev + apr_bags*(new_rate-cur_rate))*(1-A9) + sub_count*sub_fee -> 202162.83
A10: 0.15 | B10: =apr_rev -> 150152.25 | C10: =apr_rev + apr_bags*(new_rate-cur_rate) -> 163514.25 | D10: =(apr_rev + apr_bags*(new_rate-cur_rate))*(1-A10) -> 138987.11 | E10: =(b440_rev + b440_bags*(new_rate-cur_rate))*(1-A10) + sub_count*sub_fee + SUM('Customer Detail (Top 200)'!J5:J204) -> 138491.42 | F10: =(apr_rev + apr_bags*(new_rate-cur_rate))*(1-A10) + sub_count*sub_fee -> 193987.11
A11: 0.2 | B11: =apr_rev -> 150152.25 | C11: =apr_rev + apr_bags*(new_rate-cur_rate) -> 163514.25 | D11: =(apr_rev + apr_bags*(new_rate-cur_rate))*(1-A11) -> 130811.4 | E11: =(b440_rev + b440_bags*(new_rate-cur_rate))*(1-A11) + sub_count*sub_fee + SUM('Customer Detail (Top 200)'!J5:J204) -> 135149.16 | F11: =(apr_rev + apr_bags*(new_rate-cur_rate))*(1-A11) + sub_count*sub_fee -> 185811.4
A14: Annualized (× 12)
A15: Volume drop | B15: A | C15: B | D15: C | E15: D | F15: E
A16: =A5 -> 0 | B16: =B5*12 -> 1801827 | C16: =C5*12 -> 1962171 | D16: =D5*12 -> 1962171 | E16: =E5*12 -> 1782218.4 | F16: =F5*12 -> 2622171
A17: =A6 -> 0.025 | B17: =B6*12 -> 1801827 | C17: =C6*12 -> 1962171 | D17: =D6*12 -> 1913116.7 | E17: =E6*12 -> 1762164.8 | F17: =F6*12 -> 2573116.7
A18: =A7 -> 0.05 | B18: =B7*12 -> 1801827 | C18: =C7*12 -> 1962171 | D18: =D7*12 -> 1864062.4 | E18: =E7*12 -> 1742111.3 | F18: =F7*12 -> 2524062.5
A19: =A8 -> 0.075 | B19: =B8*12 -> 1801827 | C19: =C8*12 -> 1962171 | D19: =D8*12 -> 1815008.2 | E19: =E8*12 -> 1722057.7 | F19: =F8*12 -> 2475008.2
A20: =A9 -> 0.1 | B20: =B9*12 -> 1801827 | C20: =C9*12 -> 1962171 | D20: =D9*12 -> 1765953.9 | E20: =E9*12 -> 1702004.2 | F20: =F9*12 -> 2425953.9
A21: =A10 -> 0.15 | B21: =B10*12 -> 1801827 | C21: =C10*12 -> 1962171 | D21: =D10*12 -> 1667845.4 | E21: =E10*12 -> 1661897 | F21: =F10*12 -> 2327845.4
A22: =A11 -> 0.2 | B22: =B11*12 -> 1801827 | C22: =C11*12 -> 1962171 | D22: =D11*12 -> 1569736.8 | E22: =E11*12 -> 1621789.9 | F22: =F11*12 -> 2229736.8
